facebook_json_message_data_parser_public-1.1.0.dist-info/METADATA
facebook_json_message_data_parser_public-1.1.0.dist-info/WHEEL
facebook_json_message_data_parser_public-1.1.0.dist-info/entry_points.txt
facebook_json_message_data_parser_public/__init__.py
facebook_json_message_data_parser_public/facebook_json_message_data_parser.py
facebook_json_message_data_parser_public/lib/__init__.py
facebook_json_message_data_parser_public/lib/decoder.py
facebook_json_message_data_parser_public/lib/utils.py
facebook_json_message_data_parser_public/mongo/models.py
facebook_json_message_data_parser_public/mongo/mongo_handler.py
facebook_json_message_data_parser_public-1.1.0.dist-info/RECORD
