Metadata-Version: 2.1
Name: facebook-json-message-data-parser-public
Version: 1.1.0
Summary: Facebook JSON Message Parser and MongoDB Uploader
Author-Email: tadeasf <business@tadeasfort.com>
Requires-Python: >=3.8
Requires-Dist: tqdm>=4.67.1
Requires-Dist: pymongo>=4.11.1
